fpga/alu.v
module ALU(
    input wire CLK, RST_X,
    input wire [31:0] rrs1, rrs2, imm,
    input wire [4:0] instr_type,
    input wire [2:0] funct3,
    input wire [6:0] funct7,
    output wire [31:0] w_res
);
    `include "instr_type.hv"
    `include "alu.hv"
    
    reg [31:0] r_res;
    wire signed [31:0] s_imm = $signed(imm);
    wire signed [31:0] s_rrs1 = $signed(rrs1);
    wire signed [31:0] s_rrs2 = $signed(rrs2);

    always @(*) begin
        if (!RST_X) begin
            r_res <= #5 0;
        end else begin
            case ({ instr_type, funct3 })
                { OP_IMM, FUNCT3_ADDI  }: r_res <= #5 rrs1 + imm;
                { OP_IMM, FUNCT3_SLTI  }: r_res <= #5 { 31'b0, (s_rrs1 < s_imm ? 1'b1 : 1'b0) };
                { OP_IMM, FUNCT3_SLTIU }: r_res <= #5 { 31'b0, (rrs1 < imm ? 1'b1 : 1'b0) };
                { OP_IMM, FUNCT3_XORI  }: r_res <= #5 rrs1 ^ imm;
                { OP_IMM, FUNCT3_ORI   }: r_res <= #5 rrs1 | imm;
                { OP_IMM, FUNCT3_ANDI  }: r_res <= #5 rrs1 & imm;
                { OP_IMM, FUNCT3_SLLI  }: r_res <= #5 rrs1 << imm;
                { OP_IMM, FUNCT3_SRI   }: r_res <= #5 (funct7 == FUNCT7_SRLI ? (rrs1 >> imm) :
                                                       funct7 == FUNCT7_SRAI ? (s_rrs1 >>> s_imm) :
                                                                              0);
                { OP, FUNCT3_ADD }: r_res <= #5 (funct7 == FUNCT7_ADD ? rrs1 + rrs2 :
                                                 funct7 == FUNCT7_SUB ? rrs1 - rrs2 :
                                                                        0);
                { OP, FUNCT3_SLL  }: r_res <= #5 rrs1 << rrs2;
                { OP, FUNCT3_SLT  }: r_res <= #5 { 31'b0, (s_rrs1 < s_rrs2 ? 1'b1 : 1'b0) };
                { OP, FUNCT3_SLTU }: r_res <= #5 { 31'b0, (rrs1 < rrs2 ? 1'b1 : 1'b0) };
                { OP, FUNCT3_XOR  }: r_res <= #5 rrs1 ^ rrs2;
                { OP, FUNCT3_SR   }: r_res <= #5 (funct7 == FUNCT7_SRL ? rrs1 >> rrs2[4:0] :
                                                  funct7 == FUNCT7_SRA ? s_rrs1 >> rrs2 :
                                                                         0);
                { OP, FUNCT3_OR   }: r_res <= #5 rrs1 | rrs2;
                { OP, FUNCT3_AND  }: r_res <= #5 rrs1 & rrs2;
                default: r_res <= #5 0;
            endcase
        end
    end

    assign #5 w_res = r_res;

endmodule

fpga/regfile.v
module REGFILE(
    input wire CLK, RST_X,
    input wire we,
    input wire [4:0] rs1, rs2, rd,
    input wire [31:0] wd,
    output wire [31:0] rrs1, rrs2, a0
);
    reg [31:0] x[0:31];

    always @(posedge RST_X) x[0] <= #5 0;

    always @(negedge CLK) if (RST_X && we) x[rd] <= #5 wd;

    assign #5 rrs1 = (RST_X ? x[rs1] : 32'h0);
    assign #5 rrs2 = (RST_X ? x[rs2] : 32'h0);
    assign #5 a0 = (RST_X ? x[5'd10] : 32'h0);  // return value
endmodule

fpga/extend_imm.v
module EXTEND_IMM(
    input wire [31:0] instr,
    input wire [2:0] instr_format,
    output wire [31:0] imm
);
    `include "instr_type.hv"

    wire [11:0] #5 imm12 = (instr_format == I_TYPE ? instr[31:20] :
                            instr_format == S_TYPE ? { instr[31:25], instr[11:7] } : 0);
    wire [12:0] #5 imm13 = (instr_format == B_TYPE ? { instr[31], instr[7], instr[30:25], instr[11:8], 1'b0 } : 0);
    wire [19:0] #5 imm20 = (instr_format == J_TYPE ? { instr[31], instr[19:12], instr[20], instr[30:21], 1'b0 } : 0);

    assign #5 imm = (instr_format == R_TYPE ? 32'd0 :
                     instr_format == I_TYPE ? { {20{imm12[11]}}, imm12[11:0] } :
                     instr_format == S_TYPE ? { {20{imm12[11]}}, imm12[11:0] } :
                     instr_format == B_TYPE ? { {19{imm13[12]}}, imm13[12:0] } :
                     instr_format == U_TYPE ? { instr[31:12], 12'd0 } :
                     instr_format == J_TYPE ? { {12{imm20[19]}}, imm20[19:0] } :
                                              32'd0);
endmodule

fpga/instr_type.v
module INSTR_TYPE(
    input wire [4:0] opcode,
    output wire [2:0] instr_format,
    output wire [4:0] instr_type
);
    `include "instr_type.hv"
    wire [1:0] #5 base_opcode_map_row = opcode[4:3];
    wire [2:0] #5 base_opcode_map_col = opcode[2:0];
    
    assign #5 { instr_format, instr_type } = f(base_opcode_map_row, base_opcode_map_col);
    
    function [7:0] f(input [1:0] in0, input[2:0] in1);
        case (in1)
            3'b000: f = #5 (in0 == 2'b00 ? { I_TYPE, LOAD } :
                            in0 == 2'b01 ? { S_TYPE, STORE } :
                            in0 == 2'b10 ? { R4_TYPE, MADD } :     // FIXME : what's MADD ??
                                           { B_TYPE, BRANCH });

            3'b001: f = #5 (in0 == 2'b11 ? { I_TYPE, JALR } :
                                           { I_TYPE, JALR });      // FIXME
                            
            3'b010: f = #5 (in0 == 2'b10 ? { I_TYPE, NMSUB } :
                                           { I_TYPE, NMSUB });     // FIXME
            3'b011: f = #5 (in0 == 2'b11 ? { J_TYPE, JAL } :
                                           { J_TYPE, JAL});        // FIXME
            3'b100: f = #5 (in0 == 2'b00 ? { I_TYPE, OP_IMM } :
                            in0 == 2'b01 ? { R_TYPE, OP } :
                                           { R_TYPE, OP });        // FIXME
            3'b101: f = #5 (in0 == 2'b01 ? { U_TYPE, LUI } :
                                           { U_TYPE, LUI });       // FIXME
            3'b110: f = #5 (in0 == 2'b00 ? { I_TYPE, OP_IMM_32 } :
                            in0 == 2'b01 ? { R_TYPE, OP_32 } :
                                           { R_TYPE, OP_32 });     // FIXME
            default: f = #5 3'b0;
        endcase
    endfunction
endmodule

fpga/decoder.v
module INSTR_DECODER(
    input wire [31:0] instr,
    output wire [4:0] rs1, rs2, rd,
    output wire [31:0] imm,
    output wire [2:0] funct3,
    output wire [6:0] funct7,
    output wire [4:0] instr_type,
    output wire [2:0] instr_format
);
    assign #5 rs1 = instr[19:15];
    assign #5 rs2 = instr[24:20];
    assign #5 rd = instr[11:7];
    assign #5 funct3 = instr[14:12];
    assign #5 funct7 = instr[31:25];
    
    wire [4:0] #5 opcode = instr[6:2];
 
    INSTR_TYPE instr_t(opcode, instr_format, instr_type);
    EXTEND_IMM extend_imm(instr, instr_format, imm);
endmodule

fpga/cpu.v
module CPU(
    input wire CLK, RST_X,
    input wire [31:0] PC,
    input wire [31:0] instr
);
    `include "instr_type.hv"

    wire [4:0] rs1, rs2, rd;
    wire [31:0] rrs1, rrs2, imm, a0;
    wire [2:0] funct3;
    wire [6:0] funct7;
    wire [4:0] instr_type;
    wire [2:0] instr_format;
    wire [31:0] result;

    INSTR_DECODER decoder(
        .instr(instr),
        .rs1(rs1),
        .rs2(rs2),
        .rd(rd),
        .imm(imm),
        .funct3(funct3),
        .funct7(funct7),
        .instr_type(instr_type),
        .instr_format(instr_format)
    );

    REGFILE regfile(
        .CLK(CLK),
        .RST_X(RST_X),
        .we(we),
        .rs1(rs1),
        .rs2(rs2),
        .rd(rd),
        .wd(result),
        .rrs1(rrs1),
        .rrs2(rrs2),
        .a0(a0)
    );

    assign #5 we = ((instr_format == R_TYPE ||
                     instr_format == I_TYPE ||
                     instr_format == U_TYPE ||
                     instr_format == J_TYPE) ? 1'b1 : 1'b0);

    ALU alu(
        .CLK(CLK),
        .RST_X(RST_X),
        .rrs1(rrs1),
        .rrs2(rrs2),
        .imm(imm),
        .instr_type(instr_type),
        .funct3(funct3),
        .funct7(funct7),
        .w_res(result)
    );

endmodule

fpga/imem.v
module IMEM(
    input wire CLK, RST_X,
    input wire [31:0] addr,
    output wire [31:0] out_data
);
    reg [31:0] mem[0:1024];
    assign #5 out_data = (RST_X ? mem[addr[11:2]] : 0);
endmodule

fpga/top.v
`default_nettype none

module top();
    reg CLK, RST_X;
    initial begin CLK = 1; forever #50 CLK = ~CLK; end
    initial begin RST_X = 0; #125 RST_X = 1;       end
    initial begin #900 $finish();                  end
    initial begin $dumpfile("wave.vcd"); $dumpvars(0, p); end

    initial begin
        p.imem.mem[0] = 32'd0;
        p.imem.mem[1] = { 12'd10, 5'd0, 3'b0, 5'd5, 7'b0010011 };
        p.imem.mem[2] = { 12'd32, 5'd0, 3'b0, 5'd6, 7'b0010011 };
        p.imem.mem[3] = { 7'd0, 5'd6, 5'd5, 3'b0, 5'd7, 7'b0110011 }; 
    end
    
    always @(CLK) begin
        $write("%d: %d %d %d %d %d %d %d %d %d %d %d\n", 
                $stime, RST_X, p.cpu.we,
                p.cpu.rs1, p.cpu.rs2, p.cpu.rd,
                p.cpu.regfile.x[5], p.cpu.regfile.x[6], p.cpu.regfile.x[7],
                p.cpu.rrs1, p.cpu.rrs2,
                p.cpu.result);
    end

    PROCESSOR p(CLK, RST_X);
endmodule


module PROCESSOR(
    input wire CLK,
    input wire RST_X
);
    reg [31:0] PC;
    wire [31:0] instr;

    always @(posedge RST_X) PC <= #5 0;
    always @(posedge CLK) if (RST_X) PC <= #5 PC + 4;

    IMEM imem(CLK, RST_X, PC, instr);
    CPU cpu(CLK, RST_X, PC, instr);
endmodule

fpga/wave.vcd
$date
	Mon Dec 21 18:09:09 2020
$end
$version
	Icarus Verilog
$end
$timescale
	1s
$end
$scope module top $end
$scope module p $end
$var wire 1 ! CLK $end
$var wire 1 " RST_X $end
$var wire 32 # instr [31:0] $end
$var reg 32 $ PC [31:0] $end
$scope module cpu $end
$var wire 1 ! CLK $end
$var wire 32 % PC [31:0] $end
$var wire 1 " RST_X $end
$var wire 1 & we $end
$var wire 5 ' rs2 [4:0] $end
$var wire 5 ( rs1 [4:0] $end
$var wire 32 ) rrs2 [31:0] $end
$var wire 32 * rrs1 [31:0] $end
$var wire 32 + result [31:0] $end
$var wire 5 , rd [4:0] $end
$var wire 5 - instr_type [4:0] $end
$var wire 3 . instr_format [2:0] $end
$var wire 32 / instr [31:0] $end
$var wire 32 0 imm [31:0] $end
$var wire 7 1 funct7 [6:0] $end
$var wire 3 2 funct3 [2:0] $end
$var wire 32 3 a0 [31:0] $end
$scope module alu $end
$var wire 1 ! CLK $end
$var wire 1 " RST_X $end
$var wire 32 4 w_res [31:0] $end
$var wire 32 5 s_rrs2 [31:0] $end
$var wire 32 6 s_rrs1 [31:0] $end
$var wire 32 7 s_imm [31:0] $end
$var wire 32 8 rrs2 [31:0] $end
$var wire 32 9 rrs1 [31:0] $end
$var wire 5 : instr_type [4:0] $end
$var wire 32 ; imm [31:0] $end
$var wire 7 < funct7 [6:0] $end
$var wire 3 = funct3 [2:0] $end
$var reg 32 > r_res [31:0] $end
$upscope $end
$scope module decoder $end
$var wire 5 ? rs2 [4:0] $end
$var wire 5 @ rs1 [4:0] $end
$var wire 5 A rd [4:0] $end
$var wire 5 B opcode [4:0] $end
$var wire 5 C instr_type [4:0] $end
$var wire 3 D instr_format [2:0] $end
$var wire 32 E instr [31:0] $end
$var wire 32 F imm [31:0] $end
$var wire 7 G funct7 [6:0] $end
$var wire 3 H funct3 [2:0] $end
$scope module extend_imm $end
$var wire 3 I instr_format [2:0] $end
$var wire 32 J instr [31:0] $end
$var wire 20 K imm20 [19:0] $end
$var wire 13 L imm13 [12:0] $end
$var wire 12 M imm12 [11:0] $end
$var wire 32 N imm [31:0] $end
$upscope $end
$scope module instr_t $end
$var wire 5 O opcode [4:0] $end
$var wire 5 P instr_type [4:0] $end
$var wire 3 Q instr_format [2:0] $end
$var wire 2 R base_opcode_map_row [1:0] $end
$var wire 3 S base_opcode_map_col [2:0] $end
$scope function f $end
$var reg 2 T in0 [1:0] $end
$var reg 3 U in1 [2:0] $end
$upscope $end
$upscope $end
$upscope $end
$scope module regfile $end
$var wire 1 ! CLK $end
$var wire 1 " RST_X $end
$var wire 5 V rd [4:0] $end
$var wire 5 W rs1 [4:0] $end
$var wire 5 X rs2 [4:0] $end
$var wire 32 Y wd [31:0] $end
$var wire 1 & we $end
$var wire 32 Z rrs2 [31:0] $end
$var wire 32 [ rrs1 [31:0] $end
$var wire 32 \ a0 [31:0] $end
$upscope $end
$upscope $end
$scope module imem $end
$var wire 1 ! CLK $end
$var wire 1 " RST_X $end
$var wire 32 ] addr [31:0] $end
$var wire 32 ^ out_data [31:0] $end
$upscope $end
$upscope $end
$upscope $end
$enddefinitions $end
#0
$dumpvars
bx ^
bx ]
bx \
bx [
bx Z
bx Y
bx X
bx W
bx V
bx U
bx T
bx S
bx R
bx Q
bx P
bx O
bx N
bx M
bx L
bx K
bx J
bx I
bx H
bx G
bx F
bx E
bx D
bx C
bx B
bx A
bx @
bx ?
bx >
bx =
bx <
bx ;
bx :
bx 9
bx 8
bx 7
bx 6
bx 5
bx 4
bx 3
bx 2
bx 1
bx 0
bx /
bx .
bx -
bx ,
bx +
bx *
bx )
bx (
bx '
x&
bx %
bx $
bx #
0"
1!
$end
#5
b0 >
b0 #
b0 /
b0 E
b0 J
b0 ^
b0 *
b0 6
b0 9
b0 [
b0 3
b0 \
b0 )
b0 5
b0 8
b0 Z
bx0 K
bx0 L
#10
b0 -
b0 :
b0 C
b0 P
b0 .
b0 D
b0 I
b0 Q
b0 +
b0 4
b0 Y
b0 K
b0 M
b0 L
b0 B
b0 O
b0 1
b0 <
b0 G
b0 2
b0 =
b0 H
b0 ,
b0 A
b0 V
b0 '
b0 ?
b0 X
b0 (
b0 @
b0 W
#15
b0 U
b0 T
1&
b0 0
b0 7
b0 ;
b0 F
b0 N
b0 R
b0 S
#25
b1 .
b1 D
b1 I
b1 Q
#50
0!
#100
1!
#125
1"
#130
b0 $
b0 %
b0 ]
bx *
bx 6
bx 9
bx [
bx )
bx 5
bx 8
bx Z
bx 3
bx \
bx #
bx /
bx E
bx J
bx ^
#135
b0 #
b0 /
b0 E
b0 J
b0 ^
b0 *
b0 6
b0 9
b0 [
b0 )
b0 5
b0 8
b0 Z
bx M
bx B
bx O
bx 1
bx <
bx G
bx 2
bx =
bx H
bx ,
bx A
bx V
bx '
bx ?
bx X
bx (
bx @
bx W
#140
bx U
bx T
b0 M
bx 0
bx 7
bx ;
bx F
bx N
b0 B
b0 O
b0 1
b0 <
b0 G
b0 2
b0 =
b0 H
b0 ,
b0 A
b0 V
b0 '
b0 ?
b0 X
b0 (
b0 @
b0 W
bx R
bx S
bx )
bx 5
bx 8
bx Z
bx *
bx 6
bx 9
bx [
#145
b0 U
b0 T
b0 0
b0 7
b0 ;
b0 F
b0 N
b0 R
b0 S
b0 )
b0 5
b0 8
b0 Z
b0 *
b0 6
b0 9
b0 [
#150
b0 .
b0 D
b0 I
b0 Q
0!
#155
b1 .
b1 D
b1 I
b1 Q
#200
1!
#205
b100 $
b100 %
b100 ]
#210
b101000000000001010010011 #
b101000000000001010010011 /
b101000000000001010010011 E
b101000000000001010010011 J
b101000000000001010010011 ^
#215
b1010 M
b100 B
b100 O
b101 ,
b101 A
b101 V
b1010 '
b1010 ?
b1010 X
#220
b100 U
b1010 0
b1010 7
b1010 ;
b1010 F
b1010 N
b100 S
bx )
bx 5
bx 8
bx Z
#230
b100 -
b100 :
b100 C
b100 P
#235
b1010 >
#240
b1010 +
b1010 4
b1010 Y
#250
0!
#300
1!
#305
b1000 $
b1000 %
b1000 ]
#310
b10000000000000001100010011 #
b10000000000000001100010011 /
b10000000000000001100010011 E
b10000000000000001100010011 J
b10000000000000001100010011 ^
#315
b100000 M
b1 1
b1 <
b1 G
b110 ,
b110 A
b110 V
b0 '
b0 ?
b0 X
#320
b100000 0
b100000 7
b100000 ;
b100000 F
b100000 N
b0 )
b0 5
b0 8
b0 Z
#325
b100000 >
#330
b100000 +
b100000 4
b100000 Y
#350
0!
#400
1!
#405
b1100 $
b1100 %
b1100 ]
#410
b11000101000001110110011 #
b11000101000001110110011 /
b11000101000001110110011 E
b11000101000001110110011 J
b11000101000001110110011 ^
#415
b110 M
b1100 B
b1100 O
b0 1
b0 <
b0 G
b111 ,
b111 A
b111 V
b110 '
b110 ?
b110 X
b101 (
b101 @
b101 W
#420
b1 T
b110 0
b110 7
b110 ;
b110 F
b110 N
b1 R
b100000 )
b100000 5
b100000 8
b100000 Z
b1010 *
b1010 6
b1010 9
b1010 [
#425
b10000 >
#430
b1100 -
b1100 :
b1100 C
b1100 P
b0 .
b0 D
b0 I
b0 Q
b10000 +
b10000 4
b10000 Y
#435
b101010 >
b0 0
b0 7
b0 ;
b0 F
b0 N
b0 M
#440
b101010 +
b101010 4
b101010 Y
#450
0!
#500
1!
#505
b10000 $
b10000 %
b10000 ]
#510
bx #
bx /
bx E
bx J
bx ^
#515
bx B
bx O
bx 1
bx <
bx G
bx 2
bx =
bx H
bx ,
bx A
bx V
bx '
bx ?
bx X
bx (
bx @
bx W
#520
b0 >
bx U
bx T
bx R
bx S
bx )
bx 5
bx 8
bx Z
bx *
bx 6
bx 9
bx [
#525
b0 +
b0 4
b0 Y
#530
b0 -
b0 :
b0 C
b0 P
#550
0!
#600
1!
#605
b10100 $
b10100 %
b10100 ]
#650
0!
#700
1!
#705
b11000 $
b11000 %
b11000 ]
#750
0!
#800
1!
#805
b11100 $
b11100 %
b11100 ]
